json_tabulate/__init__.py
json_tabulate/cli.py
json_tabulate/core.py
json_tabulate-0.1.4.dist-info/METADATA
json_tabulate-0.1.4.dist-info/WHEEL
json_tabulate-0.1.4.dist-info/entry_points.txt
json_tabulate-0.1.4.dist-info/RECORD
