Metadata-Version: 2.4
Name: json-tabulate
Version: 0.1.4
Summary: Python library and CLI app that translates arbitrarily-nested JSON into CSV
Project-URL: Homepage, https://github.com/eecavanna/json-tabulate
Project-URL: Repository, https://github.com/eecavanna/json-tabulate
Requires-Python: >=3.9
Requires-Dist: typer>=0.9.0
Requires-Dist: typing-extensions>=4.15.0
